torch_dftd/__init__.py
torch_dftd/_version.py
torch_dftd/dftd3_xc_params.py
torch_dftd/py.typed
torch_dftd/torch_dftd3_calculator.py
torch_dftd/functions/__init__.py
torch_dftd/functions/dftd2.py
torch_dftd/functions/dftd3.py
torch_dftd/functions/distance.py
torch_dftd/functions/edge_extraction.py
torch_dftd/functions/smoothing.py
torch_dftd/functions/triplets.py
torch_dftd/functions/triplets_kernel.py
torch_dftd/nn/__init__.py
torch_dftd/nn/base_dftd_module.py
torch_dftd/nn/dftd2_module.py
torch_dftd/nn/dftd3_module.py
torch_dftd/nn/params/__init__.py
torch_dftd/nn/params/dftd2_params.py
torch_dftd/nn/params/dftd3_params.npz
torch_dftd/testing/__init__.py
torch_dftd/testing/damping.py
torch_dftd-0.5.2.dist-info/licenses/LICENSE
torch_dftd-0.5.2.dist-info/METADATA
torch_dftd-0.5.2.dist-info/WHEEL
torch_dftd-0.5.2.dist-info/top_level.txt
torch_dftd-0.5.2.dist-info/RECORD
