Metadata-Version: 2.4
Name: torch-dftd
Version: 0.5.2
Summary: pytorch implementation of dftd2 & dftd3
License-File: LICENSE
Requires-Dist: ase<4.0.0,>=3.18
Requires-Dist: pymatgen>=2020.1.28
Provides-Extra: develop
Requires-Dist: pysen[lint]==0.10.5; extra == "develop"
Requires-Dist: ase==3.21.1; extra == "develop"
Dynamic: description
Dynamic: description-content-type
Dynamic: license-file
Dynamic: provides-extra
Dynamic: requires-dist
Dynamic: summary
